{
	"cardType": "VIVOSAUR",
	"name": "Dilopho",
	"vivosaurData": {
		"lp": "360",
		"element": "WATER",
		"range": "CLOSE"
	},
	"effects": [
		{
			"type": "CHARGE",
			"cost": "1",
			"effect": "Your Opponent's next Recharge Charges -1 FP."
		},
		{
			"type": "ABILITY",
			"name": "Shady Deals",
			"effect": "Once per turn: You can discard 1 card from your FP Zone; your Opponent discards 1 card from their FP Zone."
		},
		{
			"type": "ATTACK",
			"name": "Dilopho Fang",
			"cost": "0",
			"power": "50"
		},
		{
			"type": "ATTACK",
			"name": "Dilopho Combo",
			"cost": "2",
			"power": "90",
			"effect": "Your Opponent reveals their hand and must place 1 Vivosaur from their hand into their FP Zone. If they cannot, deal 50 damage to a Vivosaur your opponent controls."
		},
		{
			"type": "RULING",
			"effect": "[\"S-Theropod\"]"
		}
	],
	"artist": "RED & Sleepy Salada",
	"set": "C",
	"setId": "03",
	"renderOptions": {
		"image": "assets/Card Art/Vivosaur/Dilopho.png",
		"imageOffsetY": 0
	}
}
